{
  "db_name": "PostgreSQL",
  "query": "\n            INSERT INTO workflow_schedules (workflow_id, user_id, config, next_run_at, enabled)\n            VALUES ($1, $2, $3, $4, true)\n            ON CONFLICT (workflow_id)\n            DO UPDATE SET\n                config = EXCLUDED.config,\n                next_run_at = EXCLUDED.next_run_at,\n                enabled = EXCLUDED.enabled,\n                updated_at = now()\n            ",
  "describe": {
    "columns": [],
    "parameters": {
      "Left": [
        "Uuid",
        "Uuid",
        "Jsonb",
        "Timestamptz"
      ]
    },
    "nullable": []
  },
  "hash": "aecf8617bf4f18a10105c8e174728ed93b026e11901d3688cfabc78688abf5b1"
}
